README.md
setup.py
ifdb/__init__.py
ifdb/ifindex.py
ifindex/__init__.py
ifindex/ifindex.py
ifindex.egg-info/PKG-INFO
ifindex.egg-info/SOURCES.txt
ifindex.egg-info/dependency_links.txt
ifindex.egg-info/top_level.txt