Metadata-Version: 2.1
Name: ifindex
Version: 0.0.3
Summary: some index
Home-page: 
Author: haifan
Author-email: 
Maintainer: 
Maintainer-email: 
License: MIT License
Classifier: Development Status :: 3 - Alpha
Classifier: Intended Audience :: Developers
Classifier: Topic :: Software Development :: Build Tools
Classifier: License :: OSI Approved :: MIT License
Classifier: Programming Language :: Python :: 3
Requires-Python: >=3.7
